amc/__init__.py
amc/__main__.py
amc/version.py
amc/data/__init__.py
amc/data/config/aws-monthly-costs-config.yaml
amc/reportexport/__init__.py
amc/runmodes/__init__.py
amc/runmodes/account/__init__.py
amc/runmodes/bu/__init__.py
amc/runmodes/service/__init__.py
aws_monthly_costs-0.0.13.dist-info/LICENSE.md
aws_monthly_costs-0.0.13.dist-info/METADATA
aws_monthly_costs-0.0.13.dist-info/WHEEL
aws_monthly_costs-0.0.13.dist-info/entry_points.txt
aws_monthly_costs-0.0.13.dist-info/top_level.txt
aws_monthly_costs-0.0.13.dist-info/RECORD
