Metadata-Version: 2.1
Name: aws-monthly-costs
Version: 0.0.13
Summary: Retrieves AWS Monthly Costs
Author: whoDoneItAgain
Author-email: 12127434+whoDoneItAgain@users.noreply.github.com
Project-URL: Homepage, https://github.com/whodoneitagain/aws-monthly-costs
Classifier: Development Status :: 4 - Beta
Classifier: Intended Audience :: Developers
Classifier: Natural Language :: English
Classifier: Operating System :: OS Independent
Classifier: Programming Language :: Python :: 3
Classifier: Programming Language :: Python :: 3.12
Requires-Python: >=3.12
License-File: LICENSE.md
Requires-Dist: boto3
Requires-Dist: pyyaml
